bookmark_analyzer/__init__.py
bookmark_analyzer/main.py
bookmark_analyzer/prompts.py
bookmark_analyzer-2025.12.22110020.dist-info/METADATA
bookmark_analyzer-2025.12.22110020.dist-info/WHEEL
bookmark_analyzer-2025.12.22110020.dist-info/top_level.txt
bookmark_analyzer-2025.12.22110020.dist-info/RECORD
