Metadata-Version: 2.4
Name: bookmark-analyzer
Version: 2025.12.22110020
Summary: Organize bookmarks and browsing history with automated tagging and categorization.
Author-email: bookmark-analyzer <hi@eugene.plus>
License: MIT
Project-URL: Homepage, https://github.com/chigwell/bookmark-analyzer
Requires-Python: >=3.9
Requires-Dist: langchain-llm7>=0.0.0
Requires-Dist: llmatch-messages>=0.0.0
Requires-Dist: langchain-core>=0.3.0
